LICENSE
contact/__init__.py
contact/admin.py
contact/apps.py
contact/cms_apps.py
contact/context_processors.py
contact/forms.py
contact/migrations/0001_initial.py
contact/migrations/0002_auto_20200616_1318.py
contact/migrations/0003_add_climatecare_fields.py
contact/migrations/__init__.py
contact/models.py
contact/templates/base.html
contact/templates/contact/email/message.html
contact/templates/contact/email/message.txt
contact/templates/contact/index.html
contact/templates/contact/success.html
contact/tests/__init__.py
contact/tests/conftest.py
contact/tests/test_cms_apps.py
contact/tests/test_forms.py
contact/tests/test_models.py
contact/tests/test_views.py
contact/tests/urls.py
contact/urls.py
contact/views.py
giant_contact-0.6.dist-info/LICENSE
giant_contact-0.6.dist-info/WHEEL
giant_contact-0.6.dist-info/METADATA
giant_contact-0.6.dist-info/RECORD
