Metadata-Version: 2.1
Name: giant-contact
Version: 0.6
Summary: Adds a generic contact app for use with Giant projects
Home-page: https://github.com/giantmade/giant-contact
License: MIT
Keywords: contact,app
Author: Will-Hoey
Author-email: will.hoey@giantmade.com
Requires-Python: >=3.6,<4.0
Classifier: Environment :: Console
Classifier: License :: OSI Approved :: MIT License
Classifier: Operating System :: OS Independent
Classifier: Programming Language :: Python :: 3
Classifier: Programming Language :: Python :: 3.6
Classifier: Programming Language :: Python :: 3.7
Classifier: Programming Language :: Python :: 3.8
Classifier: Topic :: Software Development :: Documentation
Classifier: Topic :: Software Development :: Libraries :: Python Modules
Requires-Dist: giant-mixins
Project-URL: Repository, https://github.com/giantmade/giant-contact
